lighthouse_scoring_calculator/__init__.py
lighthouse_scoring_calculator/__main__.py
lighthouse_scoring_calculator/calculator.py
lighthouse_scoring_calculator/example.py
lighthouse_scoring_calculator/metrics.py
lighthouse_scoring_calculator/util.py
lighthouse_scoring_calculator-1.0.3.dist-info/LICENSE
lighthouse_scoring_calculator-1.0.3.dist-info/METADATA
lighthouse_scoring_calculator-1.0.3.dist-info/WHEEL
lighthouse_scoring_calculator-1.0.3.dist-info/entry_points.txt
lighthouse_scoring_calculator-1.0.3.dist-info/top_level.txt
lighthouse_scoring_calculator-1.0.3.dist-info/RECORD
