Metadata-Version: 2.1
Name: lighthouse-scoring-calculator
Version: 1.0.3
Summary: Calculate the Lighthouse scoring for a website
Author-email: Fabio Manz <fabio.manz@t-online.de>
License: GNU GENERAL PUBLIC LICENSE
Project-URL: Homepage, https://github.com/fabiomanz/lighthouse-scoring-calculator
Keywords: pagespeed,lighthouse,google,web,scoring,calculator
Classifier: License :: OSI Approved :: GNU General Public License v3 (GPLv3)
Classifier: Programming Language :: Python
Classifier: Programming Language :: Python :: 3
Classifier: Topic :: Internet :: WWW/HTTP :: Site Management
Classifier: Topic :: Software Development :: Libraries :: Python Modules
Classifier: Topic :: Utilities
Requires-Python: >=3.7
License-File: LICENSE
